nixeval-0.1.1.dist-info/METADATA
nixeval-0.1.1.dist-info/WHEEL
nixeval-0.1.1.dist-info/licenses/LICENSE
nixeval.libs/libgcc_s-5b5488a6.so.1
nixeval/__init__.py
nixeval/nixeval.cpython-311-arm-linux-musleabihf.so
nixeval-0.1.1.dist-info/RECORD
