Metadata-Version: 2.4
Name: nixeval
Version: 0.1.1
Classifier: Programming Language :: Rust
Classifier: Programming Language :: Python :: 3
Classifier: License :: OSI Approved :: MIT License
License-File: LICENSE
Summary: Read and write nix expressions in python
Keywords: rust,pyo3,maturin
Author: Ruben Cano Diaz <rubencanodiaz@gmail.com>
Author-email: Ruben <rubencanodiaz@gmail.com>
License: MIT
Requires-Python: >=3.7
Project-URL: Source Code, https://github.com/Rucadi/py-nixeval
